LICENCE
MANIFEST.in
readme.rst
rednose.py
setup.py
rednose.egg-info/PKG-INFO
rednose.egg-info/SOURCES.txt
rednose.egg-info/dependency_links.txt
rednose.egg-info/entry_points.txt
rednose.egg-info/requires.txt
rednose.egg-info/top_level.txt
test_files/__init__.py
test_files/basic_test_suite.py
test_files/class_test_failure.py
test_files/encoding_test.py
test_files/encoding_test_with_literals.py
test_files/new_tests.py
test_files/sample_test.py