Metadata-Version: 1.1
Name: rednose
Version: 1.3.0
Summary: coloured output for nosetests
Home-page: https://github.com/JBKahn/rednose
Author: UNKNOWN
Author-email: UNKNOWN
License: MIT
Keywords: test nosetests nose nosetest output colour console
Platform: UNKNOWN
Classifier: License :: OSI Approved :: MIT License
Classifier: Programming Language :: Python
Classifier: Programming Language :: Python :: 3
Classifier: Development Status :: 4 - Beta
Classifier: Intended Audience :: Developers
Classifier: Topic :: Software Development :: Libraries :: Python Modules
Classifier: Topic :: Software Development :: Testing
